msu_linked_list/quartus_demo/demo_step1 nogaps/V/design.sv
`define LONG_PATH_NO_GAP

parameter n     = 16,
          w_ptr = $clog2 (n);

typedef logic [w_ptr - 1:0] ptr_t;

module start_req_gen
(
  input        clk,
  input        rst,

  output ptr_t start,
  output       start_vld,
  input        start_rdy
);

  logic [3:0] n_req;

  always_ff @ (posedge clk)
    if (rst)
      n_req <= '0;
    else if (start_rdy)
      n_req <= n_req + 4'd1;

  assign start_vld = n_req != 4'd8;

  always_comb
    case (n_req)
    4'd0:    start = ptr_t' (7);
    4'd1:    start = ptr_t' (6);
    4'd2:    start = ptr_t' (2);
    4'd3:    start = ptr_t' (1);
    4'd4:    start = ptr_t' (0);
    default: start = ptr_t' (9);
    endcase

endmodule

module ptr_seq_gen
(
  input        clk,
  input        rst,

  input  ptr_t start,
  input        start_vld,
  output       start_rdy,

  output ptr_t out_ptr,
  output logic out_ptr_vld
);

	ptr_t next[n] =
  '{
     1:  5,  5:  3,  3: 10, 10: 0,
     2:  4,  4:  0,
     6:  0,
     7: 15, 15:  8,  8:  0,
     9: 14, 14: 11, 11: 13, 13: 12, 12: 0,
    default: 0
  };

  
  ptr_t cur;
  logic cur_vld;

  always_comb
  begin
    cur = '0;
    
    `ifdef LONG_PATH_NO_GAP
    // Long path, no gap
    
    if (out_ptr_vld)
      cur = next [out_ptr];

    if (cur == '0 & start_vld)
      cur = start;

    `else
    // short path, gap
    
    if (out_ptr_vld)
      cur = next [out_ptr];
    else if (start_vld)
      cur = start;

    `endif
    
    cur_vld = (cur != '0);
  end

  always_ff @ (posedge clk) begin
    if (rst) begin
      out_ptr_vld <= 0;
		out_ptr <= '0;
    end else begin
      out_ptr_vld <= cur_vld;
	   out_ptr <= cur;
	end
  end
    

  `ifdef LONG_PATH_NO_GAP
  assign start_rdy = cur == '0 | next [cur] == '0;
  `else
  assign start_rdy = ~cur_vld;
  `endif
  
endmodule

module req_gen(
  input        clk,
  input        rst,
  output ptr_t out_ptr,
  output       out_ptr_vld
);

  
  ptr_t start;
  wire start_vld, start_rdy;

  start_req_gen i_start_req_gen (.*);
  ptr_seq_gen   i_ptr_seq_gen   (.*);

endmodule

msu_linked_list/quartus_demo/demo_step1 nogaps/testbench.sv
// Code your testbench here
// or browse Examples

/*
parameter n     = 256,
          w_ptr = $clog2 (n);

typedef logic [w_ptr - 1:0] ptr_t;

*/

include "V/design.sv";

module test();
  logic clk = '0;
  logic rst;
  ptr_t out_ptr;
  wire  out_ptr_vld;

  initial begin
    $dumpfile("dump.vcd");
    $dumpvars(0);

    // $display("time\t out_ptr\t");
    // $monitor("%g\t %d\t",
    //         $time, out_ptr);
    
    rst = 1;
    repeat(2) @ (posedge clk);
    rst = 0;
    repeat(30) @ (posedge clk);
    rst=1;
    repeat(2) @ (posedge clk);
    rst = 0;
    repeat(50) @ (posedge clk);
    $finish;
  end

  int cycle = 0;
  
  always @ (posedge clk)
  begin
    $write ("%d rst=%b", cycle, rst);
    
    if (out_ptr_vld)
      $write ("%d", out_ptr);

    $display;
    
    cycle ++;
  end

  always begin
    #5 clk = ~clk;
  end

  /* 
  Для Verilog 2001:
  
  reg clk;
  
  initial
  begin
    clk = 1'b0;
    forever #5 clk = ~clk;
  end
  */
  
  req_gen i_req_gen(.*);
endmodule

msu_linked_list/quartus_demo/demo_step1 nogaps/simulation/modelsim/dump.vcd
$date
	Tue Sep 14 23:55:03 2021
$end
$version
	ModelSim Version 2020.1
$end
$timescale
	1ps
$end

$scope module test $end
$var reg 1 ! clk $end
$var reg 1 " rst $end
$var reg 4 # out_ptr [3:0] $end
$var wire 1 $ out_ptr_vld $end
$var integer 32 % cycle $end

$scope module i_req_gen $end
$var wire 1 & clk $end
$var wire 1 ' rst $end
$var reg 4 ( out_ptr [3:0] $end
$var wire 1 $ out_ptr_vld $end
$var reg 4 ) start [3:0] $end
$var wire 1 * start_vld $end
$var wire 1 + start_rdy $end

$scope module i_start_req_gen $end
$var wire 1 & clk $end
$var wire 1 ' rst $end
$var reg 4 , start [3:0] $end
$var wire 1 * start_vld $end
$var wire 1 + start_rdy $end
$var reg 4 - n_req [3:0] $end
$upscope $end

$scope module i_ptr_seq_gen $end
$var wire 1 & clk $end
$var wire 1 ' rst $end
$var wire 1 . start [3] $end
$var wire 1 / start [2] $end
$var wire 1 0 start [1] $end
$var wire 1 1 start [0] $end
$var wire 1 * start_vld $end
$var wire 1 + start_rdy $end
$var reg 4 2 out_ptr [3:0] $end
$var reg 1 3 out_ptr_vld $end
$var reg 4 4 cur [3:0] $end
$var reg 1 5 cur_vld $end
$upscope $end
$upscope $end
$upscope $end
$enddefinitions $end
#0
$dumpvars
0!
1"
b0 #
b0 (
b111 )
b111 ,
b0 -
b0 2
03
b111 4
15
b0 %
0$
1*
0+
0&
1'
11
10
1/
0.
$end
#5
1!
1&
b1 %
b111 2
b111 (
b111 #
b0 4
b111 4
#10
0!
0&
#15
1!
1&
b10 %
0"
0'
#20
0!
0&
#25
1!
1&
b11 %
13
1$
b0 4
b1111 4
#30
0!
0&
#35
1!
1&
b100 %
b1111 2
b1111 (
b1111 #
b0 4
b1000 4
1+
#40
0!
0&
#45
1!
1&
b101 %
b1 -
b1000 2
b1000 (
b1000 #
b0 4
b111 4
b110 ,
b110 )
0+
01
b0 4
b110 4
1+
#50
0!
0&
#55
1!
1&
b110 %
b10 -
b110 2
b110 (
b110 #
b0 4
b110 4
b10 ,
b10 )
0/
b0 4
b10 4
0+
#60
0!
0&
#65
1!
1&
b111 %
b10 2
b10 (
b10 #
b0 4
b100 4
1+
#70
0!
0&
#75
1!
1&
b1000 %
b11 -
b100 2
b100 (
b100 #
b0 4
b10 4
b1 ,
b1 )
0+
11
00
b0 4
b1 4
#80
0!
0&
#85
1!
1&
b1001 %
b1 2
b1 (
b1 #
b0 4
b101 4
#90
0!
0&
#95
1!
1&
b1010 %
b101 2
b101 (
b101 #
b0 4
b11 4
#100
0!
0&
#105
1!
1&
b1011 %
b11 2
b11 (
b11 #
b0 4
b1010 4
1+
#110
0!
0&
#115
1!
1&
b1100 %
b100 -
b1010 2
b1010 (
b1010 #
b0 4
b1 4
b0 ,
b0 )
0+
01
b0 4
05
1+
#120
0!
0&
#125
1!
1&
b1101 %
b101 -
03
b0 2
b0 (
0$
b0 #
b1001 ,
b1001 )
11
1.
b1001 4
15
0+
#130
0!
0&
#135
1!
1&
b1110 %
13
b1001 2
b1001 (
1$
b1001 #
b0 4
b1110 4
#140
0!
0&
#145
1!
1&
b1111 %
b1110 2
b1110 (
b1110 #
b0 4
b1011 4
#150
0!
0&
#155
1!
1&
b10000 %
b1011 2
b1011 (
b1011 #
b0 4
b1101 4
#160
0!
0&
#165
1!
1&
b10001 %
b1101 2
b1101 (
b1101 #
b0 4
b1100 4
1+
#170
0!
0&
#175
1!
1&
b10010 %
b110 -
b1100 2
b1100 (
b1100 #
b0 4
b1001 4
0+
#180
0!
0&
#185
1!
1&
b10011 %
b1001 2
b1001 (
b1001 #
b0 4
b1110 4
#190
0!
0&
#195
1!
1&
b10100 %
b1110 2
b1110 (
b1110 #
b0 4
b1011 4
#200
0!
0&
#205
1!
1&
b10101 %
b1011 2
b1011 (
b1011 #
b0 4
b1101 4
#210
0!
0&
#215
1!
1&
b10110 %
b1101 2
b1101 (
b1101 #
b0 4
b1100 4
1+
#220
0!
0&
#225
1!
1&
b10111 %
b111 -
b1100 2
b1100 (
b1100 #
b0 4
b1001 4
0+
#230
0!
0&
#235
1!
1&
b11000 %
b1001 2
b1001 (
b1001 #
b0 4
b1110 4
#240
0!
0&
#245
1!
1&
b11001 %
b1110 2
b1110 (
b1110 #
b0 4
b1011 4
#250
0!
0&
#255
1!
1&
b11010 %
b1011 2
b1011 (
b1011 #
b0 4
b1101 4
#260
0!
0&
#265
1!
1&
b11011 %
b1101 2
b1101 (
b1101 #
b0 4
b1100 4
1+
#270
0!
0&
#275
1!
1&
b11100 %
b1000 -
b1100 2
b1100 (
b1100 #
0*
b0 4
05
#280
0!
0&
#285
1!
1&
b11101 %
b1001 -
03
b0 2
b0 (
0$
b0 #
1*
b1001 4
15
0+
#290
0!
0&
#295
1!
1&
b11110 %
13
b1001 2
b1001 (
1$
b1001 #
b0 4
b1110 4
#300
0!
0&
#305
1!
1&
b11111 %
b1110 2
b1110 (
b1110 #
b0 4
b1011 4
#310
0!
0&
#315
1!
1&
b100000 %
1"
1'
b1011 2
b0 -
03
b1011 (
0$
b1011 #
b111 ,
b0 4
b1001 4
b111 )
10
1/
0.
b0 4
b111 4
#320
0!
0&
#325
1!
1&
b100001 %
b111 2
b111 (
b111 #
b0 4
b111 4
#330
0!
0&
#335
1!
1&
b100010 %
0"
0'
#340
0!
0&
#345
1!
1&
b100011 %
13
1$
b0 4
b1111 4
#350
0!
0&
#355
1!
1&
b100100 %
b1111 2
b1111 (
b1111 #
b0 4
b1000 4
1+
#360
0!
0&
#365
1!
1&
b100101 %
b1 -
b1000 2
b1000 (
b1000 #
b0 4
b111 4
b110 ,
b110 )
0+
01
b0 4
b110 4
1+
#370
0!
0&
#375
1!
1&
b100110 %
b10 -
b110 2
b110 (
b110 #
b0 4
b110 4
b10 ,
b10 )
0/
b0 4
b10 4
0+
#380
0!
0&
#385
1!
1&
b100111 %
b10 2
b10 (
b10 #
b0 4
b100 4
1+
#390
0!
0&
#395
1!
1&
b101000 %
b11 -
b100 2
b100 (
b100 #
b0 4
b10 4
b1 ,
b1 )
0+
11
00
b0 4
b1 4
#400
0!
0&
#405
1!
1&
b101001 %
b1 2
b1 (
b1 #
b0 4
b101 4
#410
0!
0&
#415
1!
1&
b101010 %
b101 2
b101 (
b101 #
b0 4
b11 4
#420
0!
0&
#425
1!
1&
b101011 %
b11 2
b11 (
b11 #
b0 4
b1010 4
1+
#430
0!
0&
#435
1!
1&
b101100 %
b100 -
b1010 2
b1010 (
b1010 #
b0 4
b1 4
b0 ,
b0 )
0+
01
b0 4
05
1+
#440
0!
0&
#445
1!
1&
b101101 %
b101 -
03
b0 2
b0 (
0$
b0 #
b1001 ,
b1001 )
11
1.
b1001 4
15
0+
#450
0!
0&
#455
1!
1&
b101110 %
13
b1001 2
b1001 (
1$
b1001 #
b0 4
b1110 4
#460
0!
0&
#465
1!
1&
b101111 %
b1110 2
b1110 (
b1110 #
b0 4
b1011 4
#470
0!
0&
#475
1!
1&
b110000 %
b1011 2
b1011 (
b1011 #
b0 4
b1101 4
#480
0!
0&
#485
1!
1&
b110001 %
b1101 2
b1101 (
b1101 #
b0 4
b1100 4
1+
#490
0!
0&
#495
1!
1&
b110010 %
b110 -
b1100 2
b1100 (
b1100 #
b0 4
b1001 4
0+
#500
0!
0&
#505
1!
1&
b110011 %
b1001 2
b1001 (
b1001 #
b0 4
b1110 4
#510
0!
0&
#515
1!
1&
b110100 %
b1110 2
b1110 (
b1110 #
b0 4
b1011 4
#520
0!
0&
#525
1!
1&
b110101 %
b1011 2
b1011 (
b1011 #
b0 4
b1101 4
#530
0!
0&
#535
1!
1&
b110110 %
b1101 2
b1101 (
b1101 #
b0 4
b1100 4
1+
#540
0!
0&
#545
1!
1&
b110111 %
b111 -
b1100 2
b1100 (
b1100 #
b0 4
b1001 4
0+
#550
0!
0&
#555
1!
1&
b111000 %
b1001 2
b1001 (
b1001 #
b0 4
b1110 4
#560
0!
0&
#565
1!
1&
b111001 %
b1110 2
b1110 (
b1110 #
b0 4
b1011 4
#570
0!
0&
#575
1!
1&
b111010 %
b1011 2
b1011 (
b1011 #
b0 4
b1101 4
#580
0!
0&
#585
1!
1&
b111011 %
b1101 2
b1101 (
b1101 #
b0 4
b1100 4
1+
#590
0!
0&
#595
1!
1&
b111100 %
b1000 -
b1100 2
b1100 (
b1100 #
0*
b0 4
05
#600
0!
0&
#605
1!
1&
b111101 %
b1001 -
03
b0 2
b0 (
0$
b0 #
1*
b1001 4
15
0+
#610
0!
0&
#615
1!
1&
b111110 %
13
b1001 2
b1001 (
1$
b1001 #
b0 4
b1110 4
#620
0!
0&
#625
1!
1&
b111111 %
b1110 2
b1110 (
b1110 #
b0 4
b1011 4
#630
0!
0&
#635
1!
1&
b1000000 %
b1011 2
b1011 (
b1011 #
b0 4
b1101 4
#640
0!
0&
#645
1!
1&
b1000001 %
b1101 2
b1101 (
b1101 #
b0 4
b1100 4
1+
#650
0!
0&
#655
1!
1&
b1000010 %
b1010 -
b1100 2
b1100 (
b1100 #
b0 4
b1001 4
0+
#660
0!
0&
#665
1!
1&
b1000011 %
b1001 2
b1001 (
b1001 #
b0 4
b1110 4
#670
0!
0&
#675
1!
1&
b1000100 %
b1110 2
b1110 (
b1110 #
b0 4
b1011 4
#680
0!
0&
#685
1!
1&
b1000101 %
b1011 2
b1011 (
b1011 #
b0 4
b1101 4
#690
0!
0&
#695
1!
1&
b1000110 %
b1101 2
b1101 (
b1101 #
b0 4
b1100 4
1+
#700
0!
0&
#705
1!
1&
b1000111 %
b1011 -
b1100 2
b1100 (
b1100 #
b0 4
b1001 4
0+
#710
0!
0&
#715
1!
1&
b1001000 %
b1001 2
b1001 (
b1001 #
b0 4
b1110 4
#720
0!
0&
#725
1!
1&
b1001001 %
b1110 2
b1110 (
b1110 #
b0 4
b1011 4
#730
0!
0&
#735
1!
1&
b1001010 %
b1011 2
b1011 (
b1011 #
b0 4
b1101 4
#740
0!
0&
#745
1!
1&
b1001011 %
b1101 2
b1101 (
b1101 #
b0 4
b1100 4
1+
#750
0!
0&
#755
1!
1&
b1001100 %
b1100 -
b1100 2
b1100 (
b1100 #
b0 4
b1001 4
0+
#760
0!
0&
#765
1!
1&
b1001101 %
b1001 2
b1001 (
b1001 #
b0 4
b1110 4
#770
0!
0&
#775
1!
1&
b1001110 %
b1110 2
b1110 (
b1110 #
b0 4
b1011 4
#780
0!
0&
#785
1!
1&
b1001111 %
b1011 2
b1011 (
b1011 #
b0 4
b1101 4
#790
0!
0&
#795
1!
1&
b1010000 %
b1101 2
b1101 (
b1101 #
b0 4
b1100 4
1+
#800
0!
0&
#805
1!
1&
b1010001 %
b1101 -
b1100 2
b1100 (
b1100 #
b0 4
b1001 4
0+
#810
0!
0&
#815
1!
1&
b1010010 %
b1001 2
b1001 (
b1001 #
b0 4
b1110 4
#820
0!
0&
#825
1!
1&
b1010011 %
b1110 2
b1110 (
b1110 #
b0 4
b1011 4
#830
0!
0&
#835
1!
1&
b1010100 %
